mgpsogui/__init__.py
mgpsogui/mgpsogui.py
mgpsogui/start.yaml
mgpsogui/gui/HomePage.py
mgpsogui/gui/OptionManager.py
mgpsogui/gui/OptionManager_backup.py
mgpsogui/gui/__init__.py
mgpsogui/gui/General/NoticeWindow.py
mgpsogui/gui/General/ParameterView.py
mgpsogui/gui/General/__init__.py
mgpsogui/gui/PlatformTab/PlatformTab.py
mgpsogui/gui/PlatformTab/__init__.py
mgpsogui/gui/RunTab/OptimalParameterView.py
mgpsogui/gui/RunTab/RunTab.py
mgpsogui/gui/RunTab/__init__.py
mgpsogui/gui/SetupTab/BoundsEditorWindow.py
mgpsogui/gui/SetupTab/BoundsList.py
mgpsogui/gui/SetupTab/CustomFunctionEditorWindow.py
mgpsogui/gui/SetupTab/CustomFunctionMetrics.py
mgpsogui/gui/SetupTab/FunctionsList.py
mgpsogui/gui/SetupTab/ListEditor.py
mgpsogui/gui/SetupTab/ListParametersView.py
mgpsogui/gui/SetupTab/OverrideParameterMetrics.py
mgpsogui/gui/SetupTab/OverrideParameterWindow.py
mgpsogui/gui/SetupTab/SamplingListView.py
mgpsogui/gui/SetupTab/SamplingNameListWindow.py
mgpsogui/gui/SetupTab/SetupTab.py
mgpsogui/gui/SetupTab/StepView.py
mgpsogui/gui/SetupTab/__init__.py
mgpsogui/gui/VisualizeTab/MatrixEditor.py
mgpsogui/gui/VisualizeTab/SideBar.py
mgpsogui/gui/VisualizeTab/VisualizeTab.py
mgpsogui/gui/VisualizeTab/__init__.py
mgpsogui/gui/defaults/__init__.py
mgpsogui/gui/defaults/optimization.json
mgpsogui/gui/defaults/sampling.json
mgpsogui/gui/defaults/sensitivity.json
mgpsogui/gui/images/collapse.png
mgpsogui/gui/images/down.png
mgpsogui/gui/images/expand.png
mgpsogui/gui/images/play.png
mgpsogui/gui/images/plus.png
mgpsogui/gui/images/refresh.png
mgpsogui/gui/images/refresh_hd.png
mgpsogui/gui/images/stop.png
mgpsogui/gui/images/test.png
mgpsogui/gui/images/trash.png
mgpsogui/gui/images/up.png
mgpsogui/gui/messages/welcome.txt
mgpsogui/util/GraphGenerator.py
mgpsogui/util/PSORunner.py
mgpsogui/util/__init__.py
mgpsogui/util/debug.py
mgpsogui/util/helpers.py
mgpsogui/util/sampler_test_driver.py
mgpsogui/util/CTkToolTip/__init__.py
mgpsogui/util/CTkToolTip/ctk_tooltip.py
mg_pso_gui-0.2.134.dist-info/METADATA
mg_pso_gui-0.2.134.dist-info/WHEEL
mg_pso_gui-0.2.134.dist-info/entry_points.txt
mg_pso_gui-0.2.134.dist-info/top_level.txt
mg_pso_gui-0.2.134.dist-info/RECORD
