Metadata-Version: 2.1
Name: mg-pso-gui
Version: 0.2.134
Summary: GUI for MG-PSO
Author: Robert Cordingly
Author-email: <rcording@uw.ed>
Keywords: python,muti-group,pso,particle,swarm,optimization,gui
Classifier: Development Status :: 1 - Planning
Classifier: Intended Audience :: Developers
Classifier: Programming Language :: Python :: 3.10
Classifier: Operating System :: Unix
Classifier: Operating System :: MacOS :: MacOS X
Classifier: Operating System :: Microsoft :: Windows
Requires-Dist: pandas
Requires-Dist: numpy
Requires-Dist: requests
Requires-Dist: tk
Requires-Dist: customtkinter
Requires-Dist: plotly
Requires-Dist: csip
Requires-Dist: csip-cosu
Requires-Dist: pillow
Requires-Dist: kaleido==0.1.0.post1; sys_platform == "win32"
Requires-Dist: kaleido; sys_platform != "win32"
